keras_retinanet/__init__.py
keras_retinanet/initializers.py
keras_retinanet/losses.py
keras_retinanet/backend/__init__.py
keras_retinanet/backend/cntk_backend.py
keras_retinanet/backend/common.py
keras_retinanet/backend/dynamic.py
keras_retinanet/backend/tensorflow_backend.py
keras_retinanet/backend/theano_backend.py
keras_retinanet/bin/__init__.py
keras_retinanet/bin/convert_model.py
keras_retinanet/bin/debug.py
keras_retinanet/bin/evaluate.py
keras_retinanet/bin/train.py
keras_retinanet/callbacks/__init__.py
keras_retinanet/callbacks/coco.py
keras_retinanet/callbacks/common.py
keras_retinanet/callbacks/eval.py
keras_retinanet/layers/__init__.py
keras_retinanet/layers/_misc.py
keras_retinanet/layers/filter_detections.py
keras_retinanet/models/__init__.py
keras_retinanet/models/densenet.py
keras_retinanet/models/mobilenet.py
keras_retinanet/models/resnet.py
keras_retinanet/models/resnet18Tiny.py
keras_retinanet/models/resnet18TinyModels.py
keras_retinanet/models/retinanet.py
keras_retinanet/models/vgg.py
keras_retinanet/models/vgg11.py
keras_retinanet/models/vgg11Model.py
keras_retinanet/models/vgg11Tiny.py
keras_retinanet/models/vgg11TinyModels.py
keras_retinanet/models/vgg13.py
keras_retinanet/models/vgg13Model.py
keras_retinanet/preprocessing/__init__.py
keras_retinanet/preprocessing/coco.py
keras_retinanet/preprocessing/csv_generator.py
keras_retinanet/preprocessing/generator.py
keras_retinanet/preprocessing/kitti.py
keras_retinanet/preprocessing/open_images.py
keras_retinanet/preprocessing/pascal_voc.py
keras_retinanet/utils/Tee.py
keras_retinanet/utils/__init__.py
keras_retinanet/utils/anchors.py
keras_retinanet/utils/coco_eval.py
keras_retinanet/utils/colors.py
keras_retinanet/utils/compute_overlap.cp37-win_amd64.pyd
keras_retinanet/utils/config.py
keras_retinanet/utils/eval.py
keras_retinanet/utils/image.py
keras_retinanet/utils/keras_version.py
keras_retinanet/utils/model.py
keras_retinanet/utils/timing.py
keras_retinanet/utils/transform.py
gkeras_retinanet-0.5.0.dist-info/LICENSE
gkeras_retinanet-0.5.0.dist-info/METADATA
gkeras_retinanet-0.5.0.dist-info/WHEEL
gkeras_retinanet-0.5.0.dist-info/entry_points.txt
gkeras_retinanet-0.5.0.dist-info/top_level.txt
gkeras_retinanet-0.5.0.dist-info/RECORD
