Metadata-Version: 2.1
Name: gkeras-retinanet
Version: 0.5.0
Summary: Keras implementation of RetinaNet object detection.
Home-page: https://github.com/fizyr/keras-retinanet
Author: Hans Gaiser
Author-email: h.gaiser@fizyr.com
Maintainer: Hans Gaiser
Maintainer-email: h.gaiser@fizyr.com
License: UNKNOWN
Platform: UNKNOWN
Requires-Dist: keras
Requires-Dist: keras-resnet
Requires-Dist: six
Requires-Dist: scipy
Requires-Dist: cython
Requires-Dist: Pillow
Requires-Dist: opencv-python
Requires-Dist: progressbar2
